[
    {
        "inputs": [
            {
                "internalType": "address",
                "name": "claimSigner",
                "type": "address"
            },
            {
                "internalType": "address",
                "name": "tokenAddress",
                "type": "address"
            }
        ],
        "stateMutability": "nonpayable",
        "type": "constructor"
    },
    {
        "anonymous": false,
        "inputs": [
            {
                "indexed": true,
                "internalType": "address",
                "name": "previousOwner",
                "type": "address"
            },
            {
                "indexed": true,
                "internalType": "address",
                "name": "newOwner",
                "type": "address"
            }
        ],
        "name": "OwnershipTransferred",
        "type": "event"
    },
    {
        "anonymous": false,
        "inputs": [
            {
                "indexed": false,
                "internalType": "address",
                "name": "account",
                "type": "address"
            },
            {
                "indexed": false,
                "internalType": "uint256[]",
                "name": "amounts",
                "type": "uint256[]"
            }
        ],
        "name": "TokensClaimed",
        "type": "event"
    },
    {
        "inputs": [],
        "name": "CLAIM_SIGNER",
        "outputs": [
            {
                "internalType": "address",
                "name": "",
                "type": "address"
            }
        ],
        "stateMutability": "view",
        "type": "function"
    },
    {
        "inputs": [
            {
                "internalType": "uint256",
                "name": "developerAmount",
                "type": "uint256"
            },
            {
                "internalType": "uint256",
                "name": "openSourceContributorAmount",
                "type": "uint256"
            },
            {
                "internalType": "uint256",
                "name": "nftContractCreatorAmount",
                "type": "uint256"
            },
            {
                "internalType": "uint256",
                "name": "gitcoinDonorAmount",
                "type": "uint256"
            },
            {
                "internalType": "uint256",
                "name": "ensHolderAmount",
                "type": "uint256"
            },
            {
                "internalType": "uint256",
                "name": "nftHolderAmount",
                "type": "uint256"
            },
            {
                "internalType": "uint256",
                "name": "memeHolderAmount",
                "type": "uint256"
            },
            {
                "internalType": "bytes",
                "name": "signature",
                "type": "bytes"
            }
        ],
        "name": "claim",
        "outputs": [],
        "stateMutability": "nonpayable",
        "type": "function"
    },
    {
        "inputs": [],
        "name": "claimActive",
        "outputs": [
            {
                "internalType": "bool",
                "name": "",
                "type": "bool"
            }
        ],
        "stateMutability": "view",
        "type": "function"
    },
    {
        "inputs": [],
        "name": "eighteenZeros",
        "outputs": [
            {
                "internalType": "uint256",
                "name": "",
                "type": "uint256"
            }
        ],
        "stateMutability": "view",
        "type": "function"
    },
    {
        "inputs": [
            {
                "internalType": "address",
                "name": "account",
                "type": "address"
            },
            {
                "internalType": "enum SbeeTokenClaim.OptionType",
                "name": "optionType",
                "type": "uint8"
            },
            {
                "internalType": "bool",
                "name": "claimed",
                "type": "bool"
            }
        ],
        "name": "emergencyOverrideClaim",
        "outputs": [],
        "stateMutability": "nonpayable",
        "type": "function"
    },
    {
        "inputs": [
            {
                "internalType": "address",
                "name": "account",
                "type": "address"
            },
            {
                "internalType": "enum SbeeTokenClaim.OptionType",
                "name": "optionType",
                "type": "uint8"
            }
        ],
        "name": "getAccount",
        "outputs": [
            {
                "internalType": "bool",
                "name": "",
                "type": "bool"
            }
        ],
        "stateMutability": "view",
        "type": "function"
    },
    {
        "inputs": [
            {
                "internalType": "enum SbeeTokenClaim.OptionType",
                "name": "optionType",
                "type": "uint8"
            }
        ],
        "name": "getOption",
        "outputs": [
            {
                "components": [
                    {
                        "internalType": "uint256",
                        "name": "totalSupply",
                        "type": "uint256"
                    },
                    {
                        "internalType": "uint256",
                        "name": "claimedSupply",
                        "type": "uint256"
                    },
                    {
                        "internalType": "uint256",
                        "name": "maxClaimableUsers",
                        "type": "uint256"
                    },
                    {
                        "internalType": "uint256",
                        "name": "claimedUsers",
                        "type": "uint256"
                    },
                    {
                        "internalType": "uint256",
                        "name": "maxClaimableAmount",
                        "type": "uint256"
                    }
                ],
                "internalType": "struct SbeeTokenClaim.Option",
                "name": "",
                "type": "tuple"
            }
        ],
        "stateMutability": "view",
        "type": "function"
    },
    {
        "inputs": [
            {
                "internalType": "address",
                "name": "",
                "type": "address"
            },
            {
                "internalType": "uint256",
                "name": "",
                "type": "uint256"
            }
        ],
        "name": "hasClaimed",
        "outputs": [
            {
                "internalType": "bool",
                "name": "",
                "type": "bool"
            }
        ],
        "stateMutability": "view",
        "type": "function"
    },
    {
        "inputs": [
            {
                "internalType": "address",
                "name": "account",
                "type": "address"
            }
        ],
        "name": "isClaimed",
        "outputs": [
            {
                "internalType": "bool",
                "name": "",
                "type": "bool"
            }
        ],
        "stateMutability": "view",
        "type": "function"
    },
    {
        "inputs": [
            {
                "internalType": "uint256",
                "name": "",
                "type": "uint256"
            }
        ],
        "name": "options",
        "outputs": [
            {
                "internalType": "uint256",
                "name": "totalSupply",
                "type": "uint256"
            },
            {
                "internalType": "uint256",
                "name": "claimedSupply",
                "type": "uint256"
            },
            {
                "internalType": "uint256",
                "name": "maxClaimableUsers",
                "type": "uint256"
            },
            {
                "internalType": "uint256",
                "name": "claimedUsers",
                "type": "uint256"
            },
            {
                "internalType": "uint256",
                "name": "maxClaimableAmount",
                "type": "uint256"
            }
        ],
        "stateMutability": "view",
        "type": "function"
    },
    {
        "inputs": [],
        "name": "owner",
        "outputs": [
            {
                "internalType": "address",
                "name": "",
                "type": "address"
            }
        ],
        "stateMutability": "view",
        "type": "function"
    },
    {
        "inputs": [],
        "name": "renounceOwnership",
        "outputs": [],
        "stateMutability": "nonpayable",
        "type": "function"
    },
    {
        "inputs": [
            {
                "internalType": "bool",
                "name": "_active",
                "type": "bool"
            }
        ],
        "name": "setClaimActive",
        "outputs": [],
        "stateMutability": "nonpayable",
        "type": "function"
    },
    {
        "inputs": [
            {
                "internalType": "enum SbeeTokenClaim.OptionType",
                "name": "optionType",
                "type": "uint8"
            },
            {
                "internalType": "uint256",
                "name": "totalSupply",
                "type": "uint256"
            },
            {
                "internalType": "uint256",
                "name": "claimedSupply",
                "type": "uint256"
            },
            {
                "internalType": "uint256",
                "name": "maxClaimableUsers",
                "type": "uint256"
            },
            {
                "internalType": "uint256",
                "name": "claimedUsers",
                "type": "uint256"
            },
            {
                "internalType": "uint256",
                "name": "maxClaimableAmount",
                "type": "uint256"
            }
        ],
        "name": "setOption",
        "outputs": [],
        "stateMutability": "nonpayable",
        "type": "function"
    },
    {
        "inputs": [],
        "name": "token",
        "outputs": [
            {
                "internalType": "contract IERC20",
                "name": "",
                "type": "address"
            }
        ],
        "stateMutability": "view",
        "type": "function"
    },
    {
        "inputs": [
            {
                "internalType": "address",
                "name": "newOwner",
                "type": "address"
            }
        ],
        "name": "transferOwnership",
        "outputs": [],
        "stateMutability": "nonpayable",
        "type": "function"
    },
    {
        "inputs": [
            {
                "internalType": "uint256",
                "name": "amount",
                "type": "uint256"
            }
        ],
        "name": "withdrawToken",
        "outputs": [],
        "stateMutability": "nonpayable",
        "type": "function"
    }
]
